libneuroml-0.6.7.dist-info/licenses/AUTHORS
libneuroml-0.6.7.dist-info/licenses/LICENSE
neuroml/__init__.py
neuroml/__version__.py
neuroml/arraymorph.py
neuroml/arraymorph_load_time_benchmark.py
neuroml/build_time_validation.py
neuroml/loaders.py
neuroml/neuro_lex_ids.py
neuroml/utils.py
neuroml/writers.py
neuroml/hdf5/DefaultNetworkHandler.py
neuroml/hdf5/NetworkBuilder.py
neuroml/hdf5/NetworkContainer.py
neuroml/hdf5/NeuroMLHdf5Parser.py
neuroml/hdf5/NeuroMLXMLParser.py
neuroml/hdf5/__init__.py
neuroml/nml/NeuroML_v2.0.xsd
neuroml/nml/NeuroML_v2.1.xsd
neuroml/nml/NeuroML_v2.2.xsd
neuroml/nml/NeuroML_v2.3.1.xsd
neuroml/nml/NeuroML_v2.3.xsd
neuroml/nml/NeuroML_v2beta1.xsd
neuroml/nml/NeuroML_v2beta2.xsd
neuroml/nml/NeuroML_v2beta3.xsd
neuroml/nml/NeuroML_v2beta4.xsd
neuroml/nml/NeuroML_v2beta5.xsd
neuroml/nml/__init__.py
neuroml/nml/annotate_nml.py
neuroml/nml/config.py
neuroml/nml/gds_imports-template.py
neuroml/nml/generateds_config.py
neuroml/nml/generatedscollector.py
neuroml/nml/generatedssupersuper.py
neuroml/nml/helper_methods.py
neuroml/nml/nml.py
libneuroml-0.6.7.dist-info/METADATA
libneuroml-0.6.7.dist-info/WHEEL
libneuroml-0.6.7.dist-info/top_level.txt
libneuroml-0.6.7.dist-info/RECORD
