Metadata-Version: 2.4
Name: libNeuroML
Version: 0.6.7
Summary: A Python library for working with NeuroML descriptions of neuronal models
Home-page: http://libneuroml.readthedocs.org/en/latest/
Author: libNeuroML authors and contributors
Author-email: vellamike@gmail.com, p.gleeson@gmail.com
License: BSD-2-Clause
Classifier: Intended Audience :: Science/Research
Classifier: License :: OSI Approved :: BSD License
Classifier: Natural Language :: English
Classifier: Operating System :: OS Independent
Classifier: Development Status :: 5 - Production/Stable
Classifier: Programming Language :: Python :: 3
Classifier: Programming Language :: Python :: 3.9
Classifier: Programming Language :: Python :: 3.10
Classifier: Programming Language :: Python :: 3.11
Classifier: Programming Language :: Python :: 3.12
Classifier: Programming Language :: Python :: 3.13
Classifier: Topic :: Scientific/Engineering :: Bio-Informatics
Classifier: Topic :: Scientific/Engineering
License-File: LICENSE
License-File: AUTHORS
Requires-Dist: lxml
Requires-Dist: networkx
Requires-Dist: numpy<2.0; python_version < "3.10"
Requires-Dist: tables; python_version < "3.10"
Requires-Dist: numpy; python_version >= "3.10"
Requires-Dist: tables>3.10; python_version >= "3.10"
Requires-Dist: natsort
Provides-Extra: test
Requires-Dist: pytest; extra == "test"
Provides-Extra: dev
Requires-Dist: wheel; extra == "dev"
Requires-Dist: generateds>=2.20a; python_version >= "3.0" and extra == "dev"
Requires-Dist: cython; extra == "dev"
Requires-Dist: numpy; extra == "dev"
Requires-Dist: networkx; extra == "dev"
Requires-Dist: flake8; extra == "dev"
Requires-Dist: pytest; extra == "dev"
Requires-Dist: ruff; extra == "dev"
Requires-Dist: natsort; extra == "dev"
Requires-Dist: pre-commit; extra == "dev"
Provides-Extra: doc
Requires-Dist: sphinxcontrib-bibtex; extra == "doc"
Requires-Dist: pydata-sphinx-theme; extra == "doc"
Requires-Dist: natsort; extra == "doc"
Provides-Extra: full
Requires-Dist: libNeuroML[test]; extra == "full"
Requires-Dist: libNeuroML[dev]; extra == "full"
Requires-Dist: libNeuroML[doc]; extra == "full"
Dynamic: license-file
